nb_log_file_handler
