Metadata-Version: 2.1
Name: nb-log-file-handler
Version: 0.2
Summary: multi process safe log file handler,both time and size rotate，benchmark fast than concurrent_log_handler 100 times
Home-page: https://github.com/ydf0509/nb_log_file_handler
Author: bfzs
Author-email: ydf0509@sohu.com
Maintainer: ydf
Maintainer-email: ydf0509@sohu.com
License: BSD License
Keywords: logging,logger,multiprocess file handler
Platform: all
Classifier: Development Status :: 4 - Beta
Classifier: Operating System :: OS Independent
Classifier: Intended Audience :: Developers
Classifier: License :: OSI Approved :: BSD License
Classifier: Programming Language :: Python
Classifier: Programming Language :: Python :: Implementation
Classifier: Topic :: Software Development :: Libraries
